immunity_controller/__init__.py
immunity_controller/admin.py
immunity_controller/base.py
immunity_controller/checks.py
immunity_controller/context_processors.py
immunity_controller/migrations.py
immunity_controller/mixins.py
immunity_controller/routing.py
immunity_controller/settings.py
immunity_controller/urls.py
immunity_controller/vpn_backends.py
immunity_controller/config/__init__.py
immunity_controller/config/admin.py
immunity_controller/config/apps.py
immunity_controller/config/crypto.py
immunity_controller/config/exceptions.py
immunity_controller/config/exportable.py
immunity_controller/config/filters.py
immunity_controller/config/handlers.py
immunity_controller/config/models.py
immunity_controller/config/settings.py
immunity_controller/config/signals.py
immunity_controller/config/tasks.py
immunity_controller/config/tasks_zerotier.py
immunity_controller/config/urls.py
immunity_controller/config/utils.py
immunity_controller/config/validators.py
immunity_controller/config/views.py
immunity_controller/config/widgets.py
immunity_controller/config/api/__init__.py
immunity_controller/config/api/download_views.py
immunity_controller/config/api/filters.py
immunity_controller/config/api/serializers.py
immunity_controller/config/api/urls.py
immunity_controller/config/api/views.py
immunity_controller/config/api/zerotier_service.py
immunity_controller/config/base/__init__.py
immunity_controller/config/base/base.py
immunity_controller/config/base/channels_consumer.py
immunity_controller/config/base/config.py
immunity_controller/config/base/device.py
immunity_controller/config/base/device_group.py
immunity_controller/config/base/multitenancy.py
immunity_controller/config/base/tag.py
immunity_controller/config/base/template.py
immunity_controller/config/base/vpn.py
immunity_controller/config/controller/__init__.py
immunity_controller/config/controller/urls.py
immunity_controller/config/controller/views.py
immunity_controller/config/fixtures/test_templates.json
immunity_controller-1.1.1.dist-info/LICENSE
immunity_controller-1.1.1.dist-info/METADATA
immunity_controller-1.1.1.dist-info/WHEEL
immunity_controller-1.1.1.dist-info/top_level.txt
immunity_controller-1.1.1.dist-info/RECORD
