Metadata-Version: 2.1
Name: immunity-controller
Version: 1.1.1
Summary: Immunity24 Controller
Home-page: http://immunity24.org
Download-URL: https://github.com/edge-servers/immunity-controller/releases
Author: Anshu S. & OpenWISP
Author-email: anshusah@hotmail.com
License: GPL3
Keywords: django,netjson,openwrt,networking,openwisp,immunity
Platform: Platform Independent
Classifier: Development Status :: 5 - Production/Stable
Classifier: Environment :: Web Environment
Classifier: Topic :: Internet :: WWW/HTTP
Classifier: Topic :: System :: Networking
Classifier: Intended Audience :: Developers
Classifier: License :: OSI Approved :: GNU General Public License v3 (GPLv3)
Classifier: Operating System :: OS Independent
Classifier: Framework :: Django
Classifier: Programming Language :: Python :: 3
License-File: LICENSE
Requires-Dist: django-sortedm2m ~=3.1.1
Requires-Dist: django-reversion ~=5.1.0
Requires-Dist: django-taggit ~=4.0.0
Requires-Dist: netjsonconfig
Requires-Dist: django-x509 ~=1.2.0
Requires-Dist: django-loci ~=1.1.0
Requires-Dist: django-flat-json-widget ~=0.3.0
Requires-Dist: immunity-users ~=1.1.0
Requires-Dist: openwisp-utils[celery,rest] ~=1.1.0
Requires-Dist: immunity-notifications ~=1.1
Requires-Dist: immunity-ipam ~=1.1
Requires-Dist: djangorestframework-gis ~=1.1
Requires-Dist: paramiko[ed25519] ~=3.4.0
Requires-Dist: scp ~=0.15.0
Requires-Dist: django-cache-memoize ~=0.2.0
Requires-Dist: shortuuid ~=1.0.13
Requires-Dist: netaddr ~=1.3.0
Requires-Dist: django-import-export ~=3.3.0
